Metadata-Version: 1.0
Name: pypershelf
Version: 0.1.2
Summary: ORM With Focus on RM. Inspired by Bookshelf.js
Home-page: https://github.com/insipidish/pypershelf
Author: insipidish
Author-email: insipidish@gmail.com
License: MIT
Platform: UNKNOWN
